README.rst
setup.cfg
setup.py
PurgoMalum.egg-info/PKG-INFO
PurgoMalum.egg-info/SOURCES.txt
PurgoMalum.egg-info/dependency_links.txt
PurgoMalum.egg-info/requires.txt
PurgoMalum.egg-info/top_level.txt
purgo_malum/__init__.py
purgo_malum/client.py
tests/__init__.py
tests/test_client.py