Metadata-Version: 1.1
Name: PurgoMalum
Version: 1.0.3
Summary: A python client for the PurgoMalum profanity filter web service
Home-page: https://github.com/kdious/purgomalum-python
Author: Kevin Dious
Author-email: kdious@yahoo.com
License: UNKNOWN
Download-URL: https://github.com/kdious/purgomalum-python/tarball/1.0.3
Keywords: profanity,filter,PurgoMalum,purgomalum,purgo_malum,purgo-malum,Purgo Malum
Platform: UNKNOWN
Classifier: Programming Language :: Python :: 2
Classifier: Programming Language :: Python :: 3
Classifier: License :: OSI Approved :: MIT License
Classifier: Operating System :: OS Independent
